streamlit_dbtree/__init__.py
streamlit_dbtree/frontend/index.html
streamlit_dbtree/frontend/main.js
streamlit_dbtree/frontend/streamlit-component-lib.js
streamlit_dbtree/frontend/style.css
streamlit_dbtree/frontend/img/db.svg
streamlit_dbtree/frontend/img/schema.svg
streamlit_dbtree/frontend/img/table.svg
streamlit_dbtree/frontend/img/view.svg
streamlit_dbtree-0.2.5.dist-info/LICENSE
streamlit_dbtree-0.2.5.dist-info/METADATA
streamlit_dbtree-0.2.5.dist-info/WHEEL
streamlit_dbtree-0.2.5.dist-info/top_level.txt
streamlit_dbtree-0.2.5.dist-info/RECORD
