Metadata-Version: 2.1
Name: streamlit-dbtree
Version: 0.2.5
Summary: Visualize Snowflake DB tree
Author: Anthony Alteirac
Author-email: anthony@alteirac.com
Requires-Python: >=3.7
License-File: LICENSE
Requires-Dist: streamlit (>=1.2)
Requires-Dist: jinja2
Requires-Dist: snowflake-connector-python
